odoo/addons/beesdoo_inventory/README.rst
odoo/addons/beesdoo_inventory/__init__.py
odoo/addons/beesdoo_inventory/__manifest__.py
odoo/addons/beesdoo_inventory/i18n/fr_BE.po
odoo/addons/beesdoo_inventory/models/__init__.py
odoo/addons/beesdoo_inventory/models/stock.py
odoo/addons/beesdoo_inventory/readme/CONTRIBUTORS.rst
odoo/addons/beesdoo_inventory/readme/DESCRIPTION.rst
odoo/addons/beesdoo_inventory/static/description/index.html
odoo/addons/beesdoo_inventory/views/stock.xml
odoo12_addon_beesdoo_inventory-12.0.1.0.0.99.dev8.dist-info/METADATA
odoo12_addon_beesdoo_inventory-12.0.1.0.0.99.dev8.dist-info/WHEEL
odoo12_addon_beesdoo_inventory-12.0.1.0.0.99.dev8.dist-info/top_level.txt
odoo12_addon_beesdoo_inventory-12.0.1.0.0.99.dev8.dist-info/RECORD
