Metadata-Version: 2.1
Name: odoo12-addon-beesdoo-inventory
Version: 12.0.1.0.0.99.dev8
Summary: Adds a responsible, a max shipping date and a button to copy quantity to stock pickings.
Home-page: https://github.com/beescoop/Obeesdoo
Author: Beescoop - Cellule IT, Coop IT Easy SCRLfs
License: AGPL-3
Platform: UNKNOWN
Classifier: Programming Language :: Python
Classifier: Framework :: Odoo
Classifier: License :: OSI Approved :: GNU Affero General Public License v3
Requires-Python: >=3.5
Requires-Dist: odoo12-addon-beesdoo-base
Requires-Dist: odoo12-addon-beesdoo-product
Requires-Dist: odoo (<12.1dev,>=12.0a)
